[
  {
    "id": "1be3f045-348f-4cd6-ba5a-b3d29ea9a8ce",
    "data": [
      {
        "text": "I\u0027m insomniac",
        "userDefined": false
      }
    ],
    "isTemplate": false,
    "count": 0,
    "updated": 0
  },
  {
    "id": "705ece4f-705a-4a7a-8205-62c23f31c2c6",
    "data": [
      {
        "text": "I can\u0027t ",
        "userDefined": false
      },
      {
        "text": "fall",
        "meta": "@sys.ignore",
        "userDefined": false
      },
      {
        "text": " asleep",
        "userDefined": false
      }
    ],
    "isTemplate": false,
    "count": 0,
    "updated": 0
  },
  {
    "id": "66c2eaaa-0285-414b-8e3a-22de281367b7",
    "data": [
      {
        "text": "I can\u0027t get to sleep",
        "userDefined": false
      }
    ],
    "isTemplate": false,
    "count": 0,
    "updated": 0
  },
  {
    "id": "c491a023-6c44-4a89-9c81-430d1b7bb4e2",
    "data": [
      {
        "text": "I\u0027",
        "userDefined": false
      },
      {
        "text": "m",
        "meta": "@sys.ignore",
        "userDefined": false
      },
      {
        "text": " insomnious",
        "userDefined": false
      }
    ],
    "isTemplate": false,
    "count": 0,
    "updated": 0
  },
  {
    "id": "58d9cab0-ade4-414b-abd2-23462bacfc52",
    "data": [
      {
        "text": "I can\u0027t get any sleep",
        "userDefined": false
      }
    ],
    "isTemplate": false,
    "count": 0,
    "updated": 0
  },
  {
    "id": "9ed76596-8ae9-4450-a39f-3717e24f3d93",
    "data": [
      {
        "text": "I can\u0027t get no sleep",
        "userDefined": false
      }
    ],
    "isTemplate": false,
    "count": 0,
    "updated": 0
  },
  {
    "id": "3bbbb719-efd7-40b8-9c92-bd0a8623ad01",
    "data": [
      {
        "text": "I\u0027",
        "userDefined": false
      },
      {
        "text": "m",
        "meta": "@sys.ignore",
        "userDefined": false
      },
      {
        "text": " sleepless",
        "userDefined": false
      }
    ],
    "isTemplate": false,
    "count": 0,
    "updated": 0
  },
  {
    "id": "1f28b15f-ae59-4778-a9e9-9435ff162057",
    "data": [
      {
        "text": "I can\u0027t ",
        "userDefined": false
      },
      {
        "text": "sleep",
        "meta": "@sys.ignore",
        "userDefined": false
      }
    ],
    "isTemplate": false,
    "count": 0,
    "updated": 0
  }
]