[
  {
    "id": "0fae783f-27ae-439e-a842-2688f56fc264",
    "data": [
      {
        "text": "great to see you too",
        "userDefined": false
      }
    ],
    "isTemplate": false,
    "count": 0,
    "updated": 0
  },
  {
    "id": "13e27918-e46e-4ae9-af62-f6dd38a4a40d",
    "data": [
      {
        "text": "glad to see you too",
        "userDefined": false
      }
    ],
    "isTemplate": false,
    "count": 1,
    "updated": 0
  },
  {
    "id": "b60ae5d4-642b-4695-adc5-df0ef0967ae3",
    "data": [
      {
        "text": "great to see you",
        "userDefined": false
      }
    ],
    "isTemplate": false,
    "count": 1,
    "updated": 0
  },
  {
    "id": "b6b7c05f-70b5-4938-8238-0e12b6060a64",
    "data": [
      {
        "text": "great to see you again",
        "userDefined": false
      }
    ],
    "isTemplate": false,
    "count": 0,
    "updated": 0
  },
  {
    "id": "133d1711-e000-40db-994e-a9acc6c53a53",
    "data": [
      {
        "text": "I\u0027m glad to see you",
        "userDefined": false
      }
    ],
    "isTemplate": false,
    "count": 0,
    "updated": 0
  },
  {
    "id": "386ded87-9a03-4c9e-881d-c1ef4a7d7021",
    "data": [
      {
        "text": "nice",
        "meta": "@sys.ignore",
        "userDefined": false
      },
      {
        "text": " to see you",
        "userDefined": false
      }
    ],
    "isTemplate": false,
    "count": 0,
    "updated": 0
  },
  {
    "id": "9ed75c5f-d407-4e1d-810c-fd0e522172ce",
    "data": [
      {
        "text": "always a pleasure to see you",
        "userDefined": false
      }
    ],
    "isTemplate": false,
    "count": 0,
    "updated": 0
  },
  {
    "id": "eae54236-ba76-4ba3-a97a-5ed7899b822a",
    "data": [
      {
        "text": "it\u0027s",
        "meta": "@sys.ignore",
        "userDefined": false
      },
      {
        "text": " ",
        "userDefined": false
      },
      {
        "text": "good",
        "meta": "@sys.ignore",
        "userDefined": false
      },
      {
        "text": " to see you too",
        "userDefined": false
      }
    ],
    "isTemplate": false,
    "count": 1,
    "updated": 0
  },
  {
    "id": "45586e29-8ca1-47e9-814a-e7069cb0bd96",
    "data": [
      {
        "text": "how ",
        "userDefined": false
      },
      {
        "text": "good",
        "meta": "@sys.ignore",
        "userDefined": false
      },
      {
        "text": " ",
        "userDefined": false
      },
      {
        "text": "it",
        "meta": "@sys.ignore",
        "userDefined": false
      },
      {
        "text": " is to see you",
        "userDefined": false
      }
    ],
    "isTemplate": false,
    "count": 1,
    "updated": 0
  },
  {
    "id": "252af94f-b532-444d-b66e-1c328ee3b69d",
    "data": [
      {
        "text": "it\u0027s",
        "meta": "@sys.ignore",
        "userDefined": false
      },
      {
        "text": " ",
        "userDefined": false
      },
      {
        "text": "good",
        "meta": "@sys.ignore",
        "userDefined": false
      },
      {
        "text": " to see you",
        "userDefined": false
      }
    ],
    "isTemplate": false,
    "count": 0,
    "updated": 0
  },
  {
    "id": "b6e4c2e0-2ecd-41a6-be24-23ff981250c3",
    "data": [
      {
        "text": "it\u0027s",
        "meta": "@sys.ignore",
        "userDefined": false
      },
      {
        "text": " ",
        "userDefined": false
      },
      {
        "text": "nice",
        "meta": "@sys.ignore",
        "userDefined": false
      },
      {
        "text": " to see you",
        "userDefined": false
      }
    ],
    "isTemplate": false,
    "count": 1,
    "updated": 0
  },
  {
    "id": "b425771f-e529-4944-a694-2124e8df0245",
    "data": [
      {
        "text": "glad to see you",
        "userDefined": false
      }
    ],
    "isTemplate": false,
    "count": 0,
    "updated": 0
  },
  {
    "id": "5b1fb8a6-da77-4098-a06e-560c46011294",
    "data": [
      {
        "text": "lovely",
        "meta": "@sys.ignore",
        "userDefined": false
      },
      {
        "text": " to see you",
        "userDefined": false
      }
    ],
    "isTemplate": false,
    "count": 0,
    "updated": 0
  },
  {
    "id": "5d204213-2056-4285-84c9-8a0f537fc399",
    "data": [
      {
        "text": "good",
        "meta": "@sys.ignore",
        "userDefined": false
      },
      {
        "text": " to see you",
        "userDefined": false
      }
    ],
    "isTemplate": false,
    "count": 1,
    "updated": 0
  },
  {
    "id": "5c7d894b-a731-4c7e-826c-e272e2a53aa1",
    "data": [
      {
        "text": "good",
        "meta": "@sys.ignore",
        "userDefined": false
      },
      {
        "text": " to see you again",
        "userDefined": false
      }
    ],
    "isTemplate": false,
    "count": 2,
    "updated": 0
  },
  {
    "id": "dc770fa6-b4b2-4e6a-922e-fa2e345e5a76",
    "data": [
      {
        "text": "nice",
        "meta": "@sys.ignore",
        "userDefined": false
      },
      {
        "text": " to see you again",
        "userDefined": false
      }
    ],
    "isTemplate": false,
    "count": 1,
    "updated": 0
  },
  {
    "id": "0d52439c-0446-43c1-9067-02f16f122c59",
    "data": [
      {
        "text": "I am glad to see you again",
        "userDefined": false
      }
    ],
    "isTemplate": false,
    "count": 0,
    "updated": 0
  }
]